signalworks/__init__.py
signalworks/dsp.py
signalworks/signalworks.py
signalworks/viterbi.py
signalworks/processors/__init__.py
signalworks/processors/activity_detector.py
signalworks/processors/convert.py
signalworks/processors/energy_estimator.py
signalworks/processors/f0_analyzer.py
signalworks/processors/filter.py
signalworks/processors/noise_reducer.py
signalworks/processors/peak_tracker.py
signalworks/processors/processing.py
signalworks/processors/spectral_discontinutiy_estimator.py
signalworks/tracking/__init__.py
signalworks/tracking/error.py
signalworks/tracking/event.py
signalworks/tracking/label.py
signalworks/tracking/metatrack.py
signalworks/tracking/multitrack.py
signalworks/tracking/partition.py
signalworks/tracking/timevalue.py
signalworks/tracking/tracking.py
signalworks/tracking/value.py
signalworks/tracking/wave.py
signalworks-0.4.0.dist-info/AUTHORS.rst
signalworks-0.4.0.dist-info/LICENSE
signalworks-0.4.0.dist-info/METADATA
signalworks-0.4.0.dist-info/WHEEL
signalworks-0.4.0.dist-info/entry_points.txt
signalworks-0.4.0.dist-info/top_level.txt
signalworks-0.4.0.dist-info/RECORD
