Metadata-Version: 2.1
Name: signalworks
Version: 0.4.0
Summary: Library to handle signal data and perform signal processing computations
Home-page: https://github.com/lxkain/signalworks
Author: Alex Kain
Author-email: lxkain@gmail.com
License: MIT license
Keywords: signalworks
Platform: UNKNOWN
Classifier: Development Status :: 2 - Pre-Alpha
Classifier: Intended Audience :: Developers
Classifier: License :: OSI Approved :: MIT License
Classifier: Natural Language :: English
Classifier: Programming Language :: Python :: 3
Classifier: Programming Language :: Python :: 3.7
Requires-Dist: numpy
Requires-Dist: scipy
Requires-Dist: numba
Requires-Dist: resampy
Provides-Extra: dev
Requires-Dist: pyedflib ; extra == 'dev'
Requires-Dist: openxdf ; extra == 'dev'
Requires-Dist: soundfile ; extra == 'dev'
Provides-Extra: extended_audio
Requires-Dist: soundfile ; extra == 'extended_audio'
Provides-Extra: label
Requires-Dist: pyedflib ; extra == 'label'
Requires-Dist: openxdf ; extra == 'label'
